Metadata-Version: 2.1
Name: anycluster
Version: 2.4.6
Summary: anycluster provides Server-Side clustering of map markers for Geodjango
Home-page: https://github.com/biodiv/anycluster
Author: Thomas Uher
Author-email: thomas.uher@sisol-systems.com
License: The MIT License
Keywords: django,cluster,kmeans,grid,server-side clustering
Platform: OS Independent
Classifier: Programming Language :: Python :: 3
Classifier: License :: OSI Approved :: MIT License
Classifier: Operating System :: OS Independent
Requires-Python: >=3.6
License-File: LICENSE
Requires-Dist: psycopg2
Requires-Dist: djangorestframework
Requires-Dist: jsonschema
